oscar_accounts/__init__.py
oscar_accounts/abstract_models.py
oscar_accounts/admin.py
oscar_accounts/apps.py
oscar_accounts/codes.py
oscar_accounts/core.py
oscar_accounts/exceptions.py
oscar_accounts/facade.py
oscar_accounts/forms.py
oscar_accounts/models.py
oscar_accounts/names.py
oscar_accounts/security.py
oscar_accounts/setup.py
oscar_accounts/test_factories.py
oscar_accounts/views.py
oscar_accounts/api/__init__.py
oscar_accounts/api/apps.py
oscar_accounts/api/decorators.py
oscar_accounts/api/errors.py
oscar_accounts/api/views.py
oscar_accounts/checkout/__init__.py
oscar_accounts/checkout/allocation.py
oscar_accounts/checkout/forms.py
oscar_accounts/checkout/gateway.py
oscar_accounts/dashboard/__init__.py
oscar_accounts/dashboard/apps.py
oscar_accounts/dashboard/forms.py
oscar_accounts/dashboard/reports.py
oscar_accounts/dashboard/views.py
oscar_accounts/management/__init__.py
oscar_accounts/management/commands/__init__.py
oscar_accounts/management/commands/close_expired_accounts.py
oscar_accounts/management/commands/oscar_accounts_init.py
oscar_accounts/migrations/0001_initial.py
oscar_accounts/migrations/0002_core_accounts.py
oscar_accounts/migrations/0003_alter_ip_address.py
oscar_accounts/migrations/0004_auto_20201109_1647.py
oscar_accounts/migrations/__init__.py
oscar_accounts/templates/accounts/balance_check.html
oscar_accounts/templates/accounts/dashboard/account_detail.html
oscar_accounts/templates/accounts/dashboard/account_form.html
oscar_accounts/templates/accounts/dashboard/account_freeze.html
oscar_accounts/templates/accounts/dashboard/account_list.html
oscar_accounts/templates/accounts/dashboard/account_thaw.html
oscar_accounts/templates/accounts/dashboard/account_top_up.html
oscar_accounts/templates/accounts/dashboard/account_withdraw.html
oscar_accounts/templates/accounts/dashboard/transfer_detail.html
oscar_accounts/templates/accounts/dashboard/transfer_list.html
oscar_accounts/templates/accounts/dashboard/partials/account_detail.html
django_oscar_accounts-3.0.1.dist-info/LICENSE
django_oscar_accounts-3.0.1.dist-info/METADATA
django_oscar_accounts-3.0.1.dist-info/WHEEL
django_oscar_accounts-3.0.1.dist-info/top_level.txt
django_oscar_accounts-3.0.1.dist-info/RECORD
